 {
        "id": 5000630,
        "name": "受傷的白犀牛",
        "text": "有人在野外的一處水草豐茂之地目擊到一隻白犀牛，疑似受傷了。",
        "tips": "",
        "mapping_id":8001048,
        "once_new":0,
        "round_number": 1,
        "waiting_round":0,
        "waiting_round_end_action":[ //儀式沒有處理，自動關閉後
        ],
        "method_settlement": "",
        "auto_begin": 0,
        "auto_result": 0, //自動執行
        "location": "野外:[1,6]",
        "icon": "rite_15",
        "tag_tips": [
            "體魄",
            "戰鬥",
            "隱匿"
        ],
        "tag_tips_up":{
            "tips":["隱匿","體魄","戰鬥","魅力"],
            "type":"fight_result"

        },
        "tips_text":[
            "需要準備充分再去處理，如果失敗了白犀牛會跑掉。",
            "通過隱匿檢定，可以不直接與白犀牛對抗。",
            "若你親自去，也許還能置入一張縱慾卡？",
            "征服或普通線 隱匿檢測>=2點成功：觸發偷襲 失敗進正面戰鬥",
            "征服或普通線 偷襲 戰鬥體魄檢測>=1點成功：白犀牛皮 失敗進正面戰鬥",
            "征服或普通線 正面戰鬥大成功 己方數值-犀牛11點>=3點成功：白犀牛皮",
            "征服或普通線 正面戰鬥小成功 己方數值-犀牛11點>=1點成功：白犀牛皮 上陣角色受傷",
            "征服或普通線 正面戰鬥不通過：犀牛逃走 上陣角色受傷",
            "縱慾線 隱匿檢測>=2點成功：觸發偷襲",
            "縱慾線 偷襲 戰鬥體魄檢測>=1點成功：俠名+2 惡名+1 獲得白犀牛。失敗進正面戰鬥",
            "縱慾線 派遣主角：獲得動物槽位",
            "縱慾線 正面戰鬥大成功 己方數值-犀牛11點>=3點成功：惡名+1 靈視+1 詛咒犀牛皮",
            "縱慾線 正面戰鬥小成功 己方數值-犀牛11點>=1點成功：惡名+1 靈視+1 詛咒犀牛皮 上陣角色受傷",
            "縱慾線 派遣主角 正面戰鬥失敗 主角魅力檢定>=2點成功：靈視+1 惡名+1 俠名+1 獲得激情+1白犀牛 獲得動物槽位 主角受傷",
            "縱慾線 派遣主角 正面戰鬥失敗 主角魅力檢定失敗：惡名+1 上陣角色受傷"
        ],
        "open_conditions": [
        ],
        "random_text": {
            "r1":"你從遠處發現了那隻白犀牛，你打算悄悄靠近，用投槍給它來個狠的",
            "r2":"你手握投槍，瞄準着白犀牛受傷的位置狠狠地投擲了出去。",
            "r3":"無奈，你們抽出身上的武器，準備和它硬剛了"
        },
        "random_text_up":{
            "r1":{
                "text":"你從遠處發現了那隻白犀牛，你打算悄悄靠近，觀察它的破綻。",
                "type":"normal_result",
                "type_tips":"你的隱匿為你提供了完整的骰子數量。",
                "low_target": 2,
                "low_target_tips": "你至少需要2點成功才能在不被察覺的情況下靠近。"
            },
            "r2":{
                "text":"你手握投槍，瞄準着白犀牛受傷的位置狠狠地投擲了出去。",
                "type":"normal_result",
                "type_tips":"你的戰鬥和體魄為你提供了完整的骰子數量。",
                "low_target": 1,
                "low_target_tips": "你至少需要1點成功才能偷襲成功。"
            },
            "r3":{
                "text":"無奈，你們抽出身上的武器，不得不和它打一場硬仗了。",
                "type":"fight_result",
                "type_tips":"你的戰鬥和體魄為你提供的骰子數量受白犀牛對應屬性的影響。",
                "low_target": 3,
                "low_target_tips": "你至少需要3點成功。"
            },
            "r4":{
                "text":"白犀牛對你深深吸了一口氣……",
                "type":"normal_result",
                "type_tips":"你的魅力為你提供了完整的骰子數量。",
                "low_target": 2,
                "low_target_tips": "你至少需要2點成功。"
            },
            "r5":{
                "text":"白犀牛對你深深吸了一口氣……",
                "type":"normal_result",
                "type_tips":"你的魅力為你提供了完整的骰子數量。",
                "low_target": 2,
                "low_target_tips": "你至少需要2點成功。"
            },
            "r6":{
                "text":"就讓我來騎上白犀牛吧！",
                "type":"normal_result",
                "type_tips":"你的戰鬥和體魄為你提供了完整的骰子數量。",
                "low_target": 1,
                "low_target_tips": "你至少需要1點成功才能偷襲成功。"
            }
        },
        "random_effect": {
        },
        "settlement_prior": [
        ],
        "settlement": [
        ],
        "settlement_extre": [
//---------------------------使用征服卡的分支
            {
                "guid":"3a101a4d-8e68-40ea-bf83-b0e55e79b37c",
                "condition": {
                    "any":{
                    "s5.征服":1,
                        "!s5":1
                    },
                    "r1:隱匿>=":[2,5]   //隱匿成功
                },
                "result_title":"",
                "result_text": "你成功地靠近白犀牛，不過，這也是不驚動它的極限位置了。\n它正在河邊飲水，身側有一道狹長的傷口，還在流着血。看來這傷很深，必定是一把利刃留下的。你心裡計較着，如果用投槍投中它的傷口，就能在最大程度地保護這張美麗犀皮的前提下將它殺死……",
                "result":
                {
                },
                "action": {
                }
            },
            {
                "guid":"9a84272d-21c3-47d8-8430-8069d2ef9674",
                "condition": {
                    "any":{
                    "s5.征服":1,
                        "!s5":1
                    },
                    "r1:隱匿>=":[2,5],   //隱匿成功
                    "r2:體魄+戰鬥>=":[1,5]   //偷襲成功，獲勝
                },
                "result_title":"你成功了",
                "result_text": "歸功於完美的體魄和戰鬥能力，投槍又狠又準地插入了白犀牛的傷口。白犀牛發出刺耳的嚎叫，發狂般地掙扎、奔跑、試圖甩掉這痛苦的利器，揚起了無盡的塵土，最終，還是失血倒地，沒有了聲息。確定它真的不會再跳起來給你一腳之後，你擦了把汗，在血腥味引來鬣狗之前迅速地把你的獵物帶走。",
                "result":
                {
                    "clean.s1":1,
                    "card":[2000329,"已擁有+1"],
                    "clean.s5":1
                },
                "action": {
                    "event_on":5300120 //激活阿迪萊的戰書
                }
            },
            {
                "guid":"6bc36a9a-a5d6-42e4-9a23-4e3ecc0f7f86",
                "condition": {
                    "any":{
                    "s5.征服":1,
                        "!s5":1
                    },
                    "r1:隱匿>=":[2,5],  //隱匿成功
                    "r2:體魄+戰鬥<":[1,5]   //偷襲失敗，進入正面戰鬥
                },
                "result_title":"你失手了",
                "result_text": "投槍飄忽地扎進水裡，驚動了這隻本就警惕的龐大生物。白犀牛昂起首來，看向了你們的位置。看來，有一場硬仗要打了。",
                "result":
                {
                },
                "action": {
                }
            },
            {
                "guid":"356dffe3-3b8e-48df-bca3-a82f498fd06b",
                "condition": {
                    "any":{
                    "s5.征服":1,
                        "!s5":1
                    },
                    "r1:隱匿>=":[2,5],  //隱匿成功
                    "r2:體魄+戰鬥<":[1,5],  //偷襲失敗，進入正面戰鬥
                    "r3:體魄+戰鬥-e(體魄+戰鬥)>=":[3,5]  //正面戰鬥大成功
                },
                "result_title":"",
                "result_text": "憑着卓越的體魄和戰鬥技巧，你們最終取得了勝利。白犀牛悲鳴着倒下，揚起一蓬塵土，終究是沒有了聲息。你擦了把汗，在血腥味引來鬣狗之前，你得趕緊把戰利品帶走。",
                "result":
                {
                    "clean.s1":1,
                    "card":[2000329,"已擁有+1"],
                    "clean.s5":1
                },
                "action": {
                    "event_on":5300120 //激活阿迪萊的戰書
                }
            },
            {
                "guid":"2b741410-62fa-46df-9f41-2bbf05c8f780",
                "condition": {
                    "any":{
                    "s5.征服":1,
                        "!s5":1
                    },
                    "r1:隱匿>=":[2,5], //隱匿成功
                    "r2:體魄+戰鬥<":[1,5],  //偷襲失敗，進入正面戰鬥
                    "r3:體魄+戰鬥-e(體魄+戰鬥)>=":[1,5],
                    "r3:體魄+戰鬥-e(體魄+戰鬥)<":[3,5]   //正面戰鬥小成功
                },
                "result_title":"",
                "result_text": "勢均力敵的戰鬥，獵物和獵人的身份在隨時切換，但最後還是你獲勝了。白犀牛悲鳴着倒下，揚起一蓬塵土，終究是沒有了聲息。你和同伴彼此攙扶着，草草處理了一下傷口。時間緊迫，在血腥味引來鬣狗之前，你們必須趕緊把戰利品帶走。",
                "result":
                {
                    "clean.s1":1,
                    "card":[2000329,"已擁有+1"],
                    "s2+equip":2000098,
                    "s3+equip":2000098,
                    "clean.s5":1
                },
                "action": {
                    "event_on":5300120 //激活阿迪萊的戰書
                }
            },
            {
                "guid":"a6c844a6-6497-40ef-9880-9a6bb74fdc29",
                "condition": {
                    "any":{
                    "s5.征服":1,
                        "!s5":1
                    },
                    "r1:隱匿>=":[2,5],   //隱匿成功
                    "r2:體魄+戰鬥<":[1,5],  //偷襲失敗，進入正面戰鬥
                    "r3:體魄+戰鬥-e(體魄+戰鬥)<":[1,5]   //正面戰鬥失敗
                },
                "result_title":"",
                "result_text": "白犀牛在你們中間橫衝直撞，最終憑藉着蠻力和強烈的求生意志逃走了。你們傷痕累累，垂頭喪氣，但至少，你們還活着……自此，你們徹底失去了白犀牛的消息。",
                "result":
                {
                    "s2+equip":2000098,
                    "s3+equip":2000098
                },
                "action": {
                    "event_on":5300129
                }
            },
            {
                "guid":"fd716803-c33c-4dc0-8e33-97fe930ac786",
                "condition": {
                    "any":{
                    "s5.征服":1,
                        "!s5":1
                    },
                    "r1:隱匿<":[2,5]   //隱匿失敗
                },
                "result_title":"",
                "result_text": "你們剛想靠近，就不小心驚動了這隻警惕的龐大生物。白犀牛昂起首來，看向了你們的位置。看來，有一場硬仗要打了。",
                "result":
                {
                },
                "action": {
                }
            },
            {
                "guid":"1b294bd5-0d1e-4c95-a2f3-4d8a7f5406b1",
                "condition": {
                    "any":{
                    "s5.征服":1,
                        "!s5":1
                    },
                    "r1:隱匿<":[2,5],  //隱匿失敗
                    "r3:體魄+戰鬥-e(體魄+戰鬥)>=":[3,5]  //正面戰鬥大成功
                },
                "result_title":"",
                "result_text": "憑着卓越的體魄和戰鬥技巧，你們最終取得了勝利。白犀牛悲鳴着倒下，揚起一蓬塵土，終究是沒有了聲息。你擦了把汗，在血腥味引來鬣狗之前，你得趕緊把戰利品帶走。",
                "result":
                {
                    "clean.s1":1,
                    "card":[2000329,"已擁有+1"],
                    "clean.s5":1
                },
                "action": {
                    "event_on":5300120 //激活阿迪萊的戰書
                }
            },
            {
                "guid":"93220af9-0372-443c-a980-1838c6201c2b",
                "condition": {
                    "any":{
                    "s5.征服":1,
                        "!s5":1
                    },
                    "r1:隱匿<":[2,5],  //隱匿失敗
                    "r3:體魄+戰鬥-e(體魄+戰鬥)>=":[1,5],
                    "r3:體魄+戰鬥-e(體魄+戰鬥)<":[3,5]  //正面戰鬥小成功
                },
                "result_title":"",
                "result_text": "勢均力敵的戰鬥，獵物和獵人的身份在隨時切換，但最後還是你獲勝了。白犀牛悲鳴着倒下，揚起一蓬塵土，終究是沒有了聲息。你和同伴彼此攙扶着，草草處理了一下傷口。時間緊迫，在血腥味引來鬣狗之前，你們必須趕緊把戰利品帶走。",
                "result":
                {
                    "clean.s1":1,
                    "card":[2000329,"已擁有+1"],
                    "s2+equip":2000098,
                    "s3+equip":2000098,
                    "clean.s5":1
                },
                "action": {
                    "event_on":5300120 //激活阿迪萊的戰書
                }
            },
            {
                "guid":"65fb408e-d386-4c9c-ac8f-8a6fea105af0",
                "condition": {
                    "any":{
                    "s5.征服":1,
                        "!s5":1
                    },
                    "r1:隱匿<":[2,5],   //隱匿失敗
                    "r3:體魄+戰鬥-e(體魄+戰鬥)<":[1,5]   //正面戰鬥失敗
                },
                "result_title":"",
                "result_text": "白犀牛在你們中間橫衝直撞，最終憑藉着蠻力和強烈的求生意志逃走了。你們傷痕累累，垂頭喪氣，但至少，你們還活着……自此，你們徹底失去了白犀牛的消息。",
                "result":
                {
                    "s2+equip":2000098,
                    "s3+equip":2000098
                },
                "action": {
                    "event_on":5300129
                }
            },
//-----------------------------使用縱慾卡的分支---------------------
            {
                "guid":"28458213-f060-490b-8386-bf79742428fb",
                "condition": {
                    "s5.縱慾":1,
                    "r1:隱匿>=":[2,5]   //隱匿成功
                },
                "result_title":"",
                "result_text": "為了用這種異想天開的方式完成縱慾卡，你下了很多工夫——包括讓皇家飼養員為自己準備了一瓶雄性犀牛的尿液。這種氣味可以迷惑犀牛，無論是為了接近它，還是……進入它。唉，為了不在這個罪惡的遊戲中傷害人類，為了博蘇丹一笑，你真是付出了太多！\n話不多說，靠着這份臭氣熏天的藥劑，你成功接近了這頭白犀牛……就如同傳言一般，它受了傷，警惕而不安——現在，你身上散發的濃烈雄性氣息讓它產生了迷惑……",
                "result":
                {
                },
                "action": {
                }
            },
            {
                "guid":"df57d932-7557-4f43-bffb-9ff962c2df90",
                "condition": {
                    "s5.縱慾":1,
                    "r1:隱匿>=":[2,5],   //隱匿成功
                    "r6:體魄+戰鬥>=":[1,5]   //偷襲成功，獲勝
                },
                "result_title":"在夕陽下奔跑",
                "result_text": "勇敢的一躍！在犀牛明白髮生了什麼之前，你成功撲到了它身後……並在合宜的位置固定了住了自己。\n這一切顯然完全超出了犀牛對這個世界的理解……你能感覺到它的緊張，無助，甚至也有一點點興奮。\n就這樣，你以自己的身體駕馭着這股非凡的野性，在荒野上奔跑……直至雙方都精疲力盡。當你將白犀牛牽到宮廷之上，向蘇丹展示這番功績時，它顯得恬靜而高貴，令群臣露出古怪的表情……蘇丹則樂不可支。",
                "result":
                {
                    "no_show":{
                        "clean.s1":1,  //移除受傷的白犀牛，不顯示刪卡效果
                    },
                    "counter+7100004":2,  //俠名+2
                    "counter+7100002":1,   //惡名+1
                    "counter+7000660":1,  //標識進入白犀牛縱慾路線
                    "card":[2001138,"已擁有+1"],  //獲得戀愛的白犀牛
                    "clean.s5":1  //刪除縱慾卡
                },
                "action": {
                    "event_on":5300129 //激活女戰士的挑戰
                }
            },
            {
                "guid":"e4d17d4e-cfd6-4cac-8d82-8648e5e6df8e",
                "condition": {
                    "s5.縱慾":1,
                    "r1:隱匿>=":[2,5],   //隱匿成功
                    "r6:體魄+戰鬥>=":[1,5] ,  //偷襲成功，獲勝
                    "s2.主角":1
                },
                "result_title":"你已征服荒野",
                "result_text": "從此，動物們都能聞到你身上那股代表力量的氣息……它們將順服於你。\n不過，話雖如此，人應該聞不到……吧？",
                "result":
                {
                    "s2+equip_slot":"animal_handling",  //獲得動物槽位
                },
                "action": {

                }
            },
            {
                "guid":"4788ef4a-2844-4ed9-aaf9-d6c488e12a0c",
                "condition": {
                    "s5.縱慾":1,
                    "r1:隱匿>=":[2,5],   //隱匿成功
                    "r6:體魄+戰鬥>=":[1,5] ,  //偷襲成功，獲勝
                    "s3.主角":1
                },
                "result_title":"你已征服荒野",
                "result_text": "從此，動物們都能聞到你身上那股代表力量的氣息……它們將順服於你。\n不過，話雖如此，人應該聞不到……吧？",
                "result":
                {
                    "s3+equip_slot":"animal_handling",  //獲得動物槽位,和上面一樣，區別是主角在哪個槽
                },
                "action": {

                }
            },
            {
                "guid":"03a2579f-a9d9-403c-a4e3-9d41e7fae5eb",
                "condition": {
                    "s5.縱慾":1,
                    "r1:隱匿>=":[2,5],  //隱匿成功
                    "r6:體魄+戰鬥<":[1,5]   //偷襲失敗，進入正面戰鬥
                },
                "result_title":"它認出了你邪惡的本質",
                "result_text": "白犀牛在很多故事中都被認為有一定聖潔的魔力，而現在看來，這些傳說所言非虛……這頭受傷的野獸躲開了你的第一次撲擊，它顯然被激怒了，咆哮了起來，而與之呼應的，你懷裡的縱慾卡也迸發出了黑暗的氣息……這玷污世界，記錄世界，玩弄世界的遊戲正在為一個從未有過的收藏品而感到興奮。",
                "result":
                {
                },
                "action": {
                }
            },
            {
                "guid":"40c85e4f-667e-45fd-ad0e-c9ed0cf396e8",
                "condition": {
                    "s5.縱慾":1,
                    "r1:隱匿>=":[2,5],  //隱匿成功
                    "r6:體魄+戰鬥<":[1,5],  //偷襲失敗，進入正面戰鬥
                    "r3:體魄+戰鬥-e(體魄+戰鬥)>=":[3,5]  //正面戰鬥大成功
                },
                "result_title":"新的收藏",
                "result_text": "最終，白犀牛倒下了，但你身後那源於邪惡遊戲的力量並沒有滿足。\n它拖拽着你疲憊的肉體，一步步走向那野獸潔白的屍體……去完成遊戲中前所未有的褻瀆之行。\n當你最終拿回身體的控制權後，這些不祥的靈氣在白犀牛皮上留下了漆黑的烙印。",
                "result":
                {
                    "counter+7000661":1,  //標識強行縱慾成功
                    "clean.s1":1,  //移除白犀牛
                    "counter+7100002":1,  //惡名+1
                    "counter+7100005":1,  //靈視+1
                    "card":[2001139,"已擁有+1"],  //獲得邪白牛皮
                    "clean.s5":1  //消除縱慾卡
                },
                "action": {
                    "event_on":5300120 //激活阿迪萊的戰書
                }
            },
            {
                "guid":"03c2d8f2-d4e2-4394-8e04-b1ea1eba0d0c",
                "condition": {
                    "s5.縱慾":1,
                    "r1:隱匿>=":[2,5], //隱匿成功
                    "r6:體魄+戰鬥<":[1,5],  //偷襲失敗，進入正面戰鬥
                    "r3:體魄+戰鬥-e(體魄+戰鬥)>=":[1,5],
                    "r3:體魄+戰鬥-e(體魄+戰鬥)<":[3,5]   //正面戰鬥小成功
                },
                "result_title":"新的收藏",
                "result_text": "最終，白犀牛倒下了，但你身後那源於邪惡遊戲的力量並沒有滿足。\n它拖拽着你傷痕累累的肉體，一步步走向那野獸潔白的屍體……去完成遊戲中前所未有的褻瀆之行。\n當你最終拿回身體的控制權後，這些不祥的靈氣在白犀牛皮上留下了漆黑的烙印。",
                "result":
                {
                    "counter+7000661":1,  //標識強行縱慾成功
                    "clean.s1":1,  //移除白犀牛
                    "counter+7100002":1,  //惡名+1
                    "counter+7100005":1,  //靈視+1
                    "card":[2001139,"已擁有+1"],  //獲得邪白牛皮
                    "clean.s5":1,  //消除縱慾卡
                    "s2+equip":2000098,
                    "s3+equip":2000098,
                },
                "action": {
                    "event_on":5300120 //激活阿迪萊的戰書
                }
            },
            {
                "guid":"adf9aca5-67a9-45e4-bfd7-86dbff4f32e3",
                "condition": {
                    "s5.縱慾":1,
                    "r1:隱匿>=":[2,5],   //隱匿成功
                    "r6:體魄+戰鬥<":[1,5],  //偷襲失敗，進入正面戰鬥
                    "r3:體魄+戰鬥-e(體魄+戰鬥)<":[1,5],   //正面戰鬥失敗
                    "s2.主角":1,  //主角在s2
                    "r4:s2.魅力<":[2,5]  //魅力失敗
                },
                "result_title":"你令這個遊戲失望了",
                "result_text": "白犀牛把你頂翻在地……只需要踩上一腳，就可以終結你的性命。但那邪惡的力量仍然試圖滿足自己的收藏欲……它激發着你身體上的氣息，用黑暗的幻覺引誘着那野獸的靈魂……最終，也許這樣的黑暗令白犀牛感到了恐懼，它放棄了攻擊你們，轉頭離開了——遠遠地，徹底地離開了這片被褻瀆的土地。",
                "result":
                {
                    "counter+7100002":1,  //惡名+1
                    "s2+equip":2000098,
                    "s3+equip":2000098
                },
                "action": {
                    "event_on":5300129
                }
            },
            {
                "guid":"66eb6c33-f396-4681-b495-9accb2e96f66",
                "condition": {
                    "s5.縱慾":1,
                    "r1:隱匿>=":[2,5],   //隱匿成功
                    "r6:體魄+戰鬥<":[1,5],  //偷襲失敗，進入正面戰鬥
                    "r3:體魄+戰鬥-e(體魄+戰鬥)<":[1,5],   //正面戰鬥失敗
                    "s2.主角":1,  //主角在s2
                    "r4:s2.魅力>=":[2,5]  //魅力成功
                },
                "result_title":"它也被黑暗所蠱惑",
                "result_text": "白犀牛把你頂翻在地……只需要踩上一腳，就可以終結你的性命。但那邪惡的力量仍然試圖滿足自己的收藏欲……它激發着你身體上的氣息，用黑暗的幻覺引誘着那野獸的靈魂……最終，白犀牛的雙目變得漆黑，黑暗彷彿提線木偶一樣牽引這你們，完成了這場史無前例的交媾。\n最後，當你將白犀牛牽到宮廷之上，向蘇丹展示這番功績時，它溫馴而呆滯，令群臣露出古怪的表情……蘇丹則樂不可支。據說有很多追蹤這頭白犀牛的獵人都被這個故事嚇跑了，沒人敢再接近你，以及你這個瘋狂的遊戲……",
                "result":
                {
                    "counter+7100005":1,  //靈視+1
                    "counter+7100002":1,  //惡名+1
                    "counter+7100004":1,  //俠名+1
                    "card":[2001138,"已擁有+1","激情+1"],  //獲得戀愛的白犀牛
                    "s2+equip_slot":"animal_handling",  //獲得動物槽位
                    "s2+equip":2000098,  //主角受傷
                },
                "action": {
                    //此處不開啓女戰士的挑戰了
                }
            },
            {
                "guid":"ff270720-ca5b-46af-8539-f59fc1938838",
                "condition": {
                    "s5.縱慾":1,
                    "r1:隱匿>=":[2,5],   //隱匿成功
                    "r6:體魄+戰鬥<":[1,5],  //偷襲失敗，進入正面戰鬥
                    "r3:體魄+戰鬥-e(體魄+戰鬥)<":[1,5],   //正面戰鬥失敗
                    "s3.主角":1,  //主角在s3
                    "r5:s3.魅力<":[2,5]  //魅力失敗
                },
                "result_title":"你令這個遊戲失望了",
                "result_text": "白犀牛把你頂翻在地……只需要踩上一腳，就可以終結你的性命。但那邪惡的力量仍然試圖滿足自己的收藏欲……它激發着你身體上的氣息，用黑暗的幻覺引誘着那野獸的靈魂……最終，也許這樣的黑暗令白犀牛感到了恐懼，它放棄了攻擊你們，轉頭離開了——遠遠地，徹底地離開了這片被褻瀆的土地。",
                "result":
                {
                    "counter+7100002":1,  //惡名+1
                    "s2+equip":2000098,
                    "s3+equip":2000098
                },
                "action": {
                    "event_on":5300129
                }
            },
            {
                "guid":"0fbc6d7b-7837-4d11-9b91-0936e99ce20c",
                "condition": {
                    "s5.縱慾":1,
                    "r1:隱匿>=":[2,5],   //隱匿成功
                    "r6:體魄+戰鬥<":[1,5],  //偷襲失敗，進入正面戰鬥
                    "r3:體魄+戰鬥-e(體魄+戰鬥)<":[1,5],   //正面戰鬥失敗
                    "s3.主角":1,  //主角在s3
                    "r5:s3.魅力>=":[2,5]  //魅力成功
                },
                "result_title":"它也被黑暗所蠱惑",
                "result_text": "白犀牛把你頂翻在地……只需要踩上一腳，就可以終結你的性命。但那邪惡的力量仍然試圖滿足自己的收藏欲……它激發着你身體上的氣息，用黑暗的幻覺引誘着那野獸的靈魂……最終，白犀牛的雙目變得漆黑，黑暗彷彿提線木偶一樣牽引這你們，完成了這場史無前例的交媾。\n最後，當你將白犀牛牽到宮廷之上，向蘇丹展示這番功績時，它溫馴而呆滯，令群臣露出古怪的表情……蘇丹則樂不可支。據說有很多追蹤這頭白犀牛的獵人都被這個故事嚇跑了，沒人敢再接近你，以及你這個瘋狂的遊戲……",
                "result":
                {
                    "counter+7100005":1,  //靈視+1
                    "counter+7100002":1,  //惡名+1
                    "counter+7100004":1,  //俠名+1
                    "card":[2001138,"已擁有+1","激情+1"],  //獲得戀愛的白犀牛
                    "s3+equip_slot":"animal_handling",  //獲得動物槽位
                    "s3+equip":2000098,  //主角受傷
                },
                "action": {
                    //此處不開啓女戰士的挑戰了
                }
            },
            {
                "guid":"4d2688be-7fce-4d41-a90f-1ec2736273b1",
                "condition": {
                    "s5.縱慾":1,
                    "r1:隱匿<":[2,5]   //隱匿失敗
                },
                "result_title":"",
                "result_text": "你們剛想靠近，就不小心驚動了這隻警惕的龐大生物。白犀牛昂起首來，看向了你們的位置。看來，有一場硬仗要打了。",
                "result":
                {
                },
                "action": {
                }
            },
            {
                "guid":"8a7097a2-9a2e-491e-a9f2-9ae91f5ce559",
                "condition": {
                    "s5.縱慾":1,
                    "r1:隱匿<":[2,5],  //隱匿失敗
                    "r3:體魄+戰鬥-e(體魄+戰鬥)>=":[3,5]  //正面戰鬥大成功
                },
                "result_title":"新的收藏",
                "result_text": "這是一場慘烈的戰鬥，白犀牛拼死抵抗，彷彿認出了你懷裡那張卡片的邪惡本質……最終，白犀牛倒在了你們的刀劍之下，但你身後那源於邪惡遊戲的力量並沒有滿足。\n它拖拽着你疲憊的肉體，一步步走向那野獸潔白的屍體……去完成遊戲中前所未有的褻瀆之行。\n當你最終拿回身體的控制權後，這些不祥的靈氣在白犀牛皮上留下了漆黑的烙印。",
                "result":
                {
                    "counter+7000661":1,  //標識強行縱慾成功
                    "clean.s1":1,  //移除白犀牛
                    "counter+7100002":1,  //惡名+1
                    "counter+7100005":1,  //靈視+1
                    "card":[2001139,"已擁有+1"],  //獲得邪白牛皮
                    "clean.s5":1  //消除縱慾卡
                },
                "action": {
                    "event_on":5300120 //激活阿迪萊的戰書
                }
            },
            {
                "guid":"fdf87fe9-1754-4c5b-95ef-cd3b69606c92",
                "condition": {
                    "s5.縱慾":1,
                    "r1:隱匿<":[2,5],  //隱匿失敗
                    "r3:體魄+戰鬥-e(體魄+戰鬥)>=":[1,5],
                    "r3:體魄+戰鬥-e(體魄+戰鬥)<":[3,5]  //正面戰鬥小成功
                },
                "result_title":"新的收藏",
                "result_text": "這是一場慘烈的戰鬥，白犀牛拼死抵抗，彷彿認出了你懷裡那張卡片的邪惡本質……最終，白犀牛倒在了你們的刀劍之下，而你也遍體鱗傷……但你身後那源於邪惡遊戲的力量並沒有滿足。\n它拖拽着你流血的肉體，一步步走向那野獸潔白的屍體……去完成遊戲中前所未有的褻瀆之行。\n當你最終拿回身體的控制權後，這些不祥的靈氣在白犀牛皮上留下了漆黑的烙印。",
                "result":
                {
                    "counter+7000661":1,  //標識強行縱慾成功
                    "clean.s1":1,  //移除白犀牛
                    "counter+7100002":1,  //惡名+1
                    "counter+7100005":1,  //靈視+1
                    "card":[2001139,"已擁有+1"],  //獲得邪白牛皮
                    "clean.s5":1,  //消除縱慾卡
                    "s2+equip":2000098,
                    "s3+equip":2000098,
                },
                "action": {
                    "event_on":5300120 //激活阿迪萊的戰書
                }
            },
            {
                "guid":"ab65ceda-057a-4392-a781-df221dda3bee",
                "condition": {
                    "s5.縱慾":1,
                    "r1:隱匿<":[2,5],   //隱匿失敗
                    "r3:體魄+戰鬥-e(體魄+戰鬥)<":[1,5] ,  //正面戰鬥失敗
                    "s2.主角":1,  //主角在s2
                    "r4:s2.魅力<":[2,5]  //魅力失敗
                },
                "result_title":"你令這個遊戲失望了",
                "result_text": "一番苦戰之後，白犀牛把你頂翻在地……只需要踩上一腳，就可以終結你的性命。但那邪惡的力量仍然試圖滿足自己的收藏欲……它激發着你身體上的氣息，用黑暗的幻覺引誘着那野獸的靈魂……最終，也許這樣的黑暗令白犀牛感到了恐懼，它放棄了攻擊你們，轉頭離開了——遠遠地，徹底地離開了這片被褻瀆的土地。",
                "result":
                {
                    "s2+equip":2000098,
                    "s3+equip":2000098
                },
                "action": {
                    "event_on":5300129
                }
            },
            {
                "guid":"dc5c255e-d0a3-4540-bcb5-49cf6f1b927a",
                "condition": {
                    "s5.縱慾":1,
                    "r1:隱匿<":[2,5],   //隱匿失敗
                    "r3:體魄+戰鬥-e(體魄+戰鬥)<":[1,5],   //正面戰鬥失敗
                    "s2.主角":1,  //主角在s2
                    "r4:s2.魅力>=":[2,5]  //魅力成功
                },
                "result_title":"它也被黑暗所蠱惑",
                "result_text": "一番苦戰之後，白犀牛把你頂翻在地……只需要踩上一腳，就可以終結你的性命。但那邪惡的力量仍然試圖滿足自己的收藏欲……它激發着你身體上的氣息，用黑暗的幻覺引誘着那野獸的靈魂……最終，白犀牛的雙目變得漆黑，黑暗彷彿提線木偶一樣牽引這你們，完成了這場史無前例的交媾。\n最後，當你將白犀牛牽到宮廷之上，向蘇丹展示這番功績時，它溫馴而呆滯，令群臣露出古怪的表情……蘇丹則樂不可支。據說有很多追蹤這頭白犀牛的獵人都被這個故事嚇跑了，沒人敢再接近你，以及你這個瘋狂的遊戲……",
                "result":
                {
                    "no_show":{
                        "clean.s1":1,  //移除受傷的白犀牛，不顯示刪卡效果
                    },
                    "counter+7100005":1,  //靈視+1
                    "counter+7100002":1,  //惡名+1
                    "counter+7100004":1,  //俠名+1
                    "card":[2001138,"已擁有+1","激情+1"],  //獲得戀愛的白犀牛
                    "s2+equip_slot":"animal_handling",  //獲得動物槽位
                    "s2+equip":2000098,  //主角受傷
                },
                "action": {
                    //此處不開啓女戰士的挑戰了
                }
            },
            {
                "guid":"81c2049f-6d36-4818-a469-ff5ea8183707",
                "condition": {
                    "s5.縱慾":1,
                    "r1:隱匿<":[2,5],   //隱匿失敗
                    "r3:體魄+戰鬥-e(體魄+戰鬥)<":[1,5] ,  //正面戰鬥失敗
                    "s3.主角":1,  //主角在s3
                    "r5:s3.魅力<":[2,5]  //魅力失敗
                },
                "result_title":"你令這個遊戲失望了",
                "result_text": "一番苦戰之後，白犀牛把你頂翻在地……只需要踩上一腳，就可以終結你的性命。但那邪惡的力量仍然試圖滿足自己的收藏欲……它激發着你身體上的氣息，用黑暗的幻覺引誘着那野獸的靈魂……最終，也許這樣的黑暗令白犀牛感到了恐懼，它放棄了攻擊你們，轉頭離開了——遠遠地，徹底地離開了這片被褻瀆的土地。",
                "result":
                {
                    "s2+equip":2000098,
                    "s3+equip":2000098
                },
                "action": {
                    "event_on":5300129
                }
            },
            {
                "guid":"015f303e-f465-496e-bdba-8b3481103f08",
                "condition": {
                    "s5.縱慾":1,
                    "r1:隱匿<":[2,5],   //隱匿失敗
                    "r3:體魄+戰鬥-e(體魄+戰鬥)<":[1,5],   //正面戰鬥失敗
                    "s3.主角":1,  //主角在s3
                    "r5:s3.魅力>=":[2,5]  //魅力成功
                },
                "result_title":"它也被黑暗所蠱惑",
                "result_text": "一番苦戰之後，白犀牛把你頂翻在地……只需要踩上一腳，就可以終結你的性命。但那邪惡的力量仍然試圖滿足自己的收藏欲……它激發着你身體上的氣息，用黑暗的幻覺引誘着那野獸的靈魂……最終，白犀牛的雙目變得漆黑，黑暗彷彿提線木偶一樣牽引這你們，完成了這場史無前例的交媾。\n最後，當你將白犀牛牽到宮廷之上，向蘇丹展示這番功績時，它溫馴而呆滯，令群臣露出古怪的表情……蘇丹則樂不可支。據說有很多追蹤這頭白犀牛的獵人都被這個故事嚇跑了，沒人敢再接近你，以及你這個瘋狂的遊戲……",
                "result":
                {
                    "no_show":{
                        "clean.s1":1,  //移除受傷的白犀牛，不顯示刪卡效果
                    },
                    "counter+7100005":1,  //靈視+1
                    "counter+7100002":1,  //惡名+1
                    "counter+7100004":1,  //俠名+1
                    "card":[2001138,"已擁有+1","激情+1"],  //獲得戀愛的白犀牛
                    "s3+equip_slot":"animal_handling",  //獲得動物槽位
                    "s3+equip":2000098,  //主角受傷
                },
                "action": {
                    //此處不開啓女戰士的挑戰了
                }
            },

        ],
        "cards_slot":
        {
            "s1":
            {
                "guid":"9fd423f8-83d9-4b63-ad12-58747c946c80",
                "condition":
                {
                    "is":2000328
                },
                "open_adsorb":1,
                "is_key":0,
                "is_empty":0,
                "is_enemy":1,
                "text":"受傷的白犀牛"
            },
            "s2":
            {
                "guid":"26352ccd-4a1e-4045-a5c1-205b9a87846f",
                "condition":
                {
                    "type":"char"
                },
                "open_adsorb":0,
                "is_key":0,
                "is_empty":0,
                "is_enemy":0,
                "text":"你可以親自，或者派遣追隨者前去捕獵這隻白犀牛",
                "pops":[
                    {
                        "condition":{
                            "f:s2.隱匿+s3.隱匿+s4.隱匿<": 2
                        },
                        "action":{
                            "pop.5000630_s2_01.self":"如果不能靠<b><color=white>【隱匿】</color></b>的能力潛伏過去，戰鬥會非常艱難"
                        }
                    },
                    {
                        "condition":{
                            "f:s2.隱匿+s3.隱匿+s4.隱匿<": 2,
                            "f:s2.體魄+s2.戰鬥+s3.體魄+s3.戰鬥+s4.體魄+s4.戰鬥+s5.體魄+s5.戰鬥-s1.體魄-s1.戰鬥<": 3
                        },
                        "action":{
                            "pop.5000630_s2_02.self":"即使是受傷了，但以目前己方的<b><color=white>【體魄】</color></b>和<b><color=white>【戰鬥】</color></b>能力，根本沒法和它匹敵。"
                        }
                    },
                    {
                        "condition":{
                            "f:s2.隱匿+s3.隱匿+s4.隱匿>=": 2,
                            "f:s2.體魄+s2.戰鬥+s3.體魄+s3.戰鬥+s4.體魄+s4.戰鬥+s5.體魄+s5.戰鬥-s1.體魄-s1.戰鬥<":1
                        },
                        "action":{
                            "pop.5000630_s2_03.self":"即使能夠依靠潛行偷襲，但以目前己方的<b><color=white>【體魄】</color></b>和<b><color=white>【戰鬥】</color></b>能力，根本沒法和它匹敵。"
                        }
                    },
                    {
                        "condition":{
                            "f:s2.隱匿+s3.隱匿+s4.隱匿>=": 2,
                            "f:s2.體魄+s2.戰鬥+s3.體魄+s3.戰鬥+s4.體魄+s4.戰鬥+s5.體魄+s5.戰鬥-s1.體魄-s1.戰鬥>=":1,
                            "!s4":1
                        },
                        "action":{
                            "pop.5000630_s2_04.self":"萬事具備，但如果有<b><color=white>【情報】</color></b>的支撐的話，可以為自己提供試錯機會，否則陰溝裡翻船就不美了。"
                        }
                    },
                    {
                        "condition":{
                            "f:s2.隱匿+s3.隱匿+s4.隱匿>=": 2,
                            "f:s2.體魄+s2.戰鬥+s3.體魄+s3.戰鬥+s4.體魄+s4.戰鬥+s5.體魄+s5.戰鬥-s1.體魄-s1.戰鬥>=":1,
                            "s4":1
                        },
                        "action":{
                            "pop.5000630_s2_05.self":"萬事具備，現在就看狩獵之神是否在我們這邊了。"
                        }
                    }
                ]
            },
            "s3":
            {
                "guid":"07b3a7c3-abb1-43ef-86ad-c1acbdf8e9c7",
                "condition":
                {
                    "type":"char"
                },
                "open_adsorb":0,
                "is_key":0,
                "is_empty":1,
                "is_enemy":0,
                "text":"你可以親自，或者派遣追隨者前去捕獵這隻白犀牛",
                "pops":[
                    {
                        "condition":{
                            "f:s2.隱匿+s3.隱匿+s4.隱匿<": 2
                        },
                        "action":{
                            "pop.5000630_s3_01.self":"如果不能靠<b><color=white>【隱匿】</color></b>的能力潛伏過去，戰鬥會非常艱難"
                        }
                    },
                    {
                        "condition":{
                            "f:s2.隱匿+s3.隱匿+s4.隱匿<": 2,
                            "f:s2.體魄+s2.戰鬥+s3.體魄+s3.戰鬥+s4.體魄+s4.戰鬥+s5.體魄+s5.戰鬥-s1.體魄-s1.戰鬥<": 3
                        },
                        "action":{
                            "pop.5000630_s3_02.self":"即使是受傷了，但以目前己方的<b><color=white>【體魄】</color></b>和<b><color=white>【戰鬥】</color></b>能力，根本沒法和它匹敵。"
                        }
                    },
                    {
                        "condition":{
                            "f:s2.隱匿+s3.隱匿+s4.隱匿>=": 2,
                            "f:s2.體魄+s2.戰鬥+s3.體魄+s3.戰鬥+s4.體魄+s4.戰鬥+s5.體魄+s5.戰鬥-s1.體魄-s1.戰鬥<":1
                        },
                        "action":{
                            "pop.5000630_s3_03.self":"即使依靠潛行，但以目前己方的<b><color=white>【體魄】</color></b>和<b><color=white>【戰鬥】</color></b>能力，根本沒法和它匹敵。"
                        }
                    },
                    {
                        "condition":{
                            "f:s2.隱匿+s3.隱匿+s4.隱匿>=": 2,
                            "f:s2.體魄+s2.戰鬥+s3.體魄+s3.戰鬥+s4.體魄+s4.戰鬥+s5.體魄+s5.戰鬥-s1.體魄-s1.戰鬥>=":1,
                            "!s4":1
                        },
                        "action":{
                            "pop.5000630_s3_04.self":"萬事具備，但如果有<b><color=white>【情報】</color></b>的支撐的話，可以為自己提供試錯機會，否則陰溝裡翻船就不美了。"
                        }
                    },
                    {
                        "condition":{
                            "f:s2.隱匿+s3.隱匿+s4.隱匿>=": 2,
                            "f:s2.體魄+s2.戰鬥+s3.體魄+s3.戰鬥+s4.體魄+s4.戰鬥+s5.體魄+s5.戰鬥-s1.體魄-s1.戰鬥>=":1,
                            "s4":1
                        },
                        "action":{
                            "pop.5000630_s3_05.self":"萬事具備，現在就看狩獵之神是否在我們這邊了。"
                        }
                    }
                ]
            },
            "s4":
            {
                "guid":"91bea19a-b9d6-4c3f-af67-05b31a7e93f7",
                "condition":
                {
                    "type":"item",
                    "cost.消耗品=":1,
                        "!金幣":1
                },
                "open_adsorb":0,
                "is_key":0,
                "is_empty":1,
                "is_enemy":0,
                "text":"有些消耗品能在戰鬥中派上用場",
                "pops":[
                    {
                        "condition":{
                            "f:s2.隱匿+s3.隱匿+s4.隱匿<": 2
                        },
                        "action":{
                            "pop.5000630_s4_01.self":"如果不能靠<b><color=white>【隱匿】</color></b>的能力潛伏過去，戰鬥會非常艱難"
                        }
                    },
                    {
                        "condition":{
                            "f:s2.隱匿+s3.隱匿+s4.隱匿<": 2,
                            "f:s2.體魄+s2.戰鬥+s3.體魄+s3.戰鬥+s4.體魄+s4.戰鬥+s5.體魄+s5.戰鬥-s1.體魄-s1.戰鬥<": 3
                        },
                        "action":{
                            "pop.5000630_s4_02.self":"即使是受傷了，但以目前己方的<b><color=white>【體魄】</color></b>和<b><color=white>【戰鬥】</color></b>能力，根本沒法和它匹敵。"
                        }
                    },
                    {
                        "condition":{
                            "f:s2.隱匿+s3.隱匿+s4.隱匿>=": 2,
                            "f:s2.體魄+s2.戰鬥+s3.體魄+s3.戰鬥+s4.體魄+s4.戰鬥+s5.體魄+s5.戰鬥-s1.體魄-s1.戰鬥<":1
                        },
                        "action":{
                            "pop.5000630_s4_03.self":"即使依靠潛行，但以目前己方的<b><color=white>【體魄】</color></b>和<b><color=white>【戰鬥】</color></b>能力，根本沒法和它匹敵。"
                        }
                    },
                    {
                        "condition":{
                            "f:s2.隱匿+s3.隱匿+s4.隱匿>=": 2,
                            "f:s2.體魄+s2.戰鬥+s3.體魄+s3.戰鬥+s4.體魄+s4.戰鬥+s5.體魄+s5.戰鬥-s1.體魄-s1.戰鬥>=":1,
                            "s4":1
                        },
                        "action":{
                            "pop.5000630_s4_04.self":"萬事具備，現在就看狩獵之神是否在我們這邊了。"
                        }
                    }
                ]
            },
            "s5":
            {
                "guid":"6ff49175-86e2-4b16-8b38-2b3832347903",
                "condition":
                {
                    "type":"sudan",
                    "any":{
                        "征服":1,
                        "all":{
                            "any":{
                                "s2.主角":1,
                                "s3.主角":1
                            },
                            "縱慾":1
                        }
                    },
                    "f:rare-s1.rare<=":0
                },
                "open_adsorb":0,
                "is_key":0,
                "is_empty":1,
                "is_enemy":0,
                "text":"你可以藉此折斷一張不高於犀牛品級的征服卡或縱慾卡"
            }
        }
    }