{
    "id": 5006153,
    "name": "品鑑王冠",
    "text": "寶冠的調整已經完成——謝天謝地——按照慣例，蘇丹邀請群臣到宮中去一同品鑑、欣賞這頂至寶。",
    "tips": "",
    "mapping_id":8001576,
    "once_new": 0,
    "round_number": 1,
    "waiting_round": 0,
    "waiting_round_end_action": [
    ],
    "method_settlement": "",
    "auto_begin": 1,
    "auto_result": 0,
    "location": "宮廷:[2,6]",
    "icon": "rite_14",
    "tag_tips": [],
    "tag_tips_up": {

    },
    "tips_text": [
        "蘇丹要展示自己的王冠，誰敢不到場？",
        "主角不在時：進入結局【無名人之死】",
        "s2-s4未全滿時：想成為最好的珠寶商線斷線",
        "s2-s4為空時：熱娜死亡"
    ],
    "open_conditions": [
    ],
    "random_text": {},
    "random_text_up": {

    },
    "settlement_prior": [
         {
            "guid":"693e6d4d-a685-422f-99ba-08724f252d47",
            "condition": {
                "!s5":1  //你真不來啊
            },
            "result_title": "你竟敢缺席這麼重要的場合！",
            "result_text": "你的缺席毫無疑問被解讀為你對他權威的蔑視，而在他的雷霆震怒之下，沒人敢幫你說話。你被處死了。",
            "result": {

            },
            "action": {
               "over":1
            }
        },
    ],
    "settlement": [
        {
            "guid":"8b3851f0-b982-4ae7-9ef3-4e8067abf403",
            "condition": {
                "s2":1,  //s2是哈桑
                "s2.is":2000460,
                "s3":1,
                "s4":1
            },
            "result_title": "讓你評價你還真評價上了",
            "result_text": "你站在人群的最前排，一眼就望見了跪在寶冠旁邊的熱娜。她看起來憔悴了不少，黑眼圈十分明顯，看起來是不眠不休地幹了三天。\n那寶冠當然做的十分完美，新的寶石被妥帖地打磨過，光澤璀璨；舊的寶石都被稍微往冠頂挪了挪，金子的部分也略減少了一些；為了容納蘇丹最近收到的那幾枚鴿卵大小的鑽石，熱娜索性為寶冠做了一個三重寶石頂，讓數枚鑽石聚在一起，燦爛有如夜晚的火光。\n蘇丹走了進來，他看了看寶冠，又看了看熱娜，而後，他轉向群臣：“諸位愛卿，你們覺得怎麼樣？”\n人群竊竊私語起來，許多人都認為這寶冠的調整做得非常好，但也有些人憎恨你、憎恨站在你這邊的熱娜，所以他們提出了各種問題：什麼鑽石切割得好像不算太完美啦、什麼金子太少不夠華美啦——甚至還有最過分的，有個人說這寶冠加上寶石頂之後就太長了，會顯得蘇丹個子矮！！\n你可真的是氣急了！！你剛要擼起袖子痛罵，[s2.name]和[s4.name]就尖銳地諷刺他的審美和品味、質疑他的道德和忠誠，[s3.name]更是不滿，他看不慣任何人為了攻擊其他勢力竟敢在這種方面詆譭偉大的蘇丹！他說着就要抽出腰間的刀劍——他可是少有的幾個有資格佩劍上朝的近衛之一呢！現在，他要為君王的榮耀而戰！\n廷臣連忙一擁而上攔住了他，那名大臣也被嚇得跪倒在地，反覆說他不是這個意思，你們兩撥人險些在朝堂上像最粗鄙的鄉野村夫那樣打起來……而蘇丹呢，蘇丹笑着目睹了這一切，他覺得十分有趣。這可比一頂花裡胡哨的帽子好玩多了！鬧到最後，他甚至從金冠上摘下來一枚金葉子賞給了你和熱娜……這可真是，這可真是不得了的賞賜啊！",
            "result": {
                "card":[2001285,"已擁有+1"],  //獲得金葉片
                "counter+7000832":1,  //獲得金葉片的計數器
            },
            "action": {
               "event_on":5320624  //開啓帝國最好的珠寶匠幕後
            }
        },
        {
            "guid":"62018a08-d76f-49d9-8513-68139af133e8",

            "condition": {
                "s2":1,  //s2是貓貓
                "s2.is":2000461,
                "s3":1,
                "s4":1
            },
            "result_title": "讓你評價你還真評價上了",
            "result_text": "你站在人群的最前排，一眼就望見了跪在寶冠旁邊的熱娜。她看起來憔悴了不少，黑眼圈十分明顯，看起來是不眠不休地幹了三天。\n那寶冠當然做的十分完美，新的寶石被妥帖地打磨過，光澤璀璨；舊的寶石都被稍微往冠頂挪了挪，金子的部分也略減少了一些；為了容納蘇丹最近收到的那幾枚鴿卵大小的鑽石，熱娜索性為寶冠做了一個三重寶石頂，讓數枚鑽石聚在一起，燦爛有如夜晚的火光。\n蘇丹走了進來，他看了看寶冠，又看了看熱娜，而後，他轉向群臣：“諸位愛卿，你們覺得怎麼樣？”\n人群竊竊私語起來，許多人都認為這寶冠的調整做得非常好，但也有些人憎恨你、憎恨站在你這邊的熱娜，所以他們提出了各種問題：什麼鑽石切割得好像不算太完美啦、什麼金子太少不夠華美啦——甚至還有最過分的，有個人說這寶冠加上寶石頂之後就太長了，會顯得蘇丹個子矮！！\n你可真的是氣急了！！你剛要擼起袖子痛罵，[s4.name]就尖銳地諷刺他的審美和品味、質疑他的道德和忠誠，[s3.name]更是不滿，他看不慣任何人為了攻擊其他勢力竟敢在這種方面詆譭偉大的蘇丹！他說着就要抽出腰間的刀劍——他可是少有的幾個有資格佩劍上朝的近衛之一呢！現在，他要為君王的榮耀而戰！\n廷臣連忙一擁而上攔住了他，但誰也都攔住英勇的貝姬夫人（你當然是氣急了才會不小心讓它掙脫你的懷抱啦），他狠狠地在那名大臣臉上撓了兩爪子呢！大臣慘叫着跌坐在地，又因為殿前失儀而被嚇得連忙跪伏下來……而蘇丹呢，蘇丹笑着目睹了這場鬧劇，他覺得十分有趣：這可比一頂花裡胡哨的帽子好玩多了！鬧到最後，他甚至從金冠上摘下來一枚金葉子賞給了你和熱娜……這可真是，這可真是不得了的賞賜啊！",
            "result": {
                "card":[2001285,"已擁有+1"],  //獲得金葉片
                "counter+7000832":1,  //獲得金葉片的計數器
            },
            "action": {
               "event_on":5320624  //開啓帝國最好的珠寶匠幕後
            }
        },
        {
            "guid":"fd3ea12c-56b0-4a83-9e06-cb201e05c1f5",
            "condition": {
                "any":{
                    "s2":1,
                    "s3":1,
                    "s4":1
                }
            },
            "result_title": "讓你評價你還真評價上了",
            "result_text": "你站在人群的最前排，一眼就望見了跪在寶冠旁邊的熱娜。她看起來憔悴了不少，黑眼圈十分明顯，看起來是不眠不休地幹了三天。\n那寶冠當然做的十分完美，新的寶石被妥帖地打磨過，光澤璀璨；舊的寶石都被稍微往冠頂挪了挪，金子的部分也略減少了一些；為了容納蘇丹最近收到的那幾枚鴿卵大小的鑽石，熱娜索性為寶冠做了一個三重寶石頂，讓數枚鑽石聚在一起，燦爛有如夜晚的火光。\n蘇丹走了進來，他看了看寶冠，又看了看熱娜。而後，他轉向群臣。\n“諸位愛卿，你們覺得怎麼樣？”\n人群竊竊私語起來，許多人都認為這寶冠的調整做得非常好，但也有些人憎恨你、憎恨站在你這邊的熱娜，所以他們提出了各種問題：什麼鑽石切割得好像不算太完美啦、什麼金子太少不夠華美啦——甚至還有最過分的，有個人說這寶冠加上寶石頂之後就太長了，會顯得蘇丹個子矮！！\n你可真的是氣急了！！\n你冷笑着，質問那位反對你的大臣，他是不是就看不慣君主偶爾真心實意地開心一下？他是不是就一定要讓偉大的蘇丹皺眉頭？蘇丹取得了如此多的功績、為帝國如此開疆拓土，他到底有什麼不滿意？他為什麼要聲稱一頂帽子就可以讓蘇丹變矮……他在暗示什麼？說啊，說清楚啊，別以為我不知道你在想什麼——說出來！為什麼會認為蘇丹矮！是不是除此之外還有其他更大逆不道的想法？是不是還覺得蘇丹其他地方不行？天啊——神啊——以帝國的金血起誓，他這樣的叛徒，你今天不當廷清君側砍了他，就對不起歷任蘇丹對你們家的深恩厚愛！\n你說着就要去抽王室衛兵腰間的刀劍。\n一群廷臣一擁而上地攔住了你，那位大臣則被嚇得跪倒在地，反覆說着他不是這個意思。而蘇丹呢，蘇丹笑着目睹了這一切，他覺得十分有趣。這可比一頂花裡胡哨的帽子好玩多了！",
            "result": {

            },
            "action": {
               "event_on":5320624  //開啓帝國最好的珠寶匠幕後
            }
        },
        {
            "guid":"5acf0870-ff52-4172-bd2a-ff71db6bad99",
            "condition": {
                "!s2":1,
                "!s3":1,
                "!s4":1
            },
            "result_title": "獨木難支",
            "result_text": "你站在人群的最前排，一眼就望見了跪在寶冠旁邊的熱娜。她看起來憔悴了不少，黑眼圈十分明顯，看起來是不眠不休地幹了三天。\n那寶冠當然做的十分完美，新的寶石被妥帖地打磨過，光澤璀璨；舊的寶石都被稍微往冠頂挪了挪，金子的部分也略減少了一些；為了容納蘇丹最近收到的那幾枚鴿卵大小的鑽石，熱娜索性為寶冠做了一個三重寶石頂，讓數枚鑽石聚在一起，燦爛有如夜晚的火光。\n蘇丹走了進來，他看了看寶冠，又看了看熱娜。而後，他轉向群臣。\n“諸位愛卿，你們覺得怎麼樣？”\n人群竊竊私語起來，許多人都認為這寶冠的調整做得非常好，但也有些人憎恨你、憎恨站在你這邊的熱娜，所以他們提出了各種問題：什麼鑽石切割得好像不算太完美啦、什麼金子太少不夠華美啦——甚至還有最過分的，有個人說這寶冠加上寶石頂之後就太長了，會顯得蘇丹個子矮！！\n你可真的是氣急了！！\n你和那位反對者在寶冠跟前吵了起來，誰都說不服誰。等你們倆回過神時，蘇丹已經微笑着旁觀很久了。\n他覺得你跟那人一樣蠢，但他就喜歡這樣。不過，話雖如此，他現在看那頂王冠也越看越不順眼了，他揮了揮手，命令衛兵把熱娜拖下去殺了。也許用她的血稍微裝點一下，這頂王冠會更美麗吧。",
            "result": {
                "clean.s1":1  //熱娜死亡
            },
            "action": {

            }
        }

    ],
    "settlement_extre": [
        {
            "guid":"4328c6af-171d-41da-8f36-9b407b64c648",
            "condition": {
                "any":{
                    "s2":1,
                    "s3":1,
                    "s4":1
                },
            },
            "result_title": "終於結束了",
            "result_text": "離開覲見廳時，所有人都下意識地離你遠了一點，畢竟他們已經實打實地見識過了你的本事。\n熱娜與你一同走出了王宮，她的腿都軟了，幾乎需要你攙扶着她，而她也對你的表現印象深刻。\n“這蘇丹的遊戲……遠比我想的更可怕……”她小聲對你說，“您能那麼快地編出那麼一大套——一定是因為您已經見識過太多次這一切了吧？[player.name]老爺，我的朋友……您可真不容易啊……”",
            "result": {
                "counter+7000833":1  //可以獲得熱娜的禮物的計數器
            },
            "action": {

            }
        },
    ],
    "cards_slot": {
        "s1": {
            "guid":"260c7699-e4a2-4a31-8640-ab49fa601f52",
            "condition": {
                "type": "char",
                "is":2000019 //熱娜
            },
            "open_adsorb": 1,
            "is_key": 0,
            "is_empty": 0,
            "is_enemy": 0,
            "text": "熱娜",
        },
        "s2": {
            "guid":"f00ddbac-7601-4f42-9c45-69ce22c2f9d7",
            "condition": {
                "type": "char",
                "any":{
                    "is":2000461,  //貝姬
                    "is":2000460  //哈桑
                }
            },
            "open_adsorb": 0,
            "is_key": 0,
            "is_empty": 1,
            "is_enemy": 0,
            "text": "一位弄臣\n貝姬夫人/哈桑：王冠上的金葉+1",
        },
        "s3": {
            "guid":"512cc08f-e2cf-4a23-80ef-2ae9e1fa2eac",
            "condition": {
                "type": "char",
                "any":{
                    "is":2000064,  //奈布哈尼
                    "is":2000054,  //哲巴爾
                    "is":2000065  //法里斯
                }
            },
            "open_adsorb": 0,
            "is_key": 0,
            "is_empty": 1,
            "is_enemy": 0,
            "text": "一名近衛\n奈布哈尼/哲巴爾/法里斯",
        },
        "s4": {
            "guid":"c961e098-33a8-4023-b4b3-9f5c7bba4d40",
            "condition": {
                "type": "char",
                "any":{
                    "is":2000055,  //娜依拉
                    "妻子":1,
                    "is":2000062,  //法圖娜
                    "all":{
                        "is":2000195,  //拉伊德
                        "變身公主":1, //拉伊德貴婦
                    }

                }
            },
            "open_adsorb": 0,
            "is_key": 0,
            "is_empty": 1,
            "is_enemy": 0,
            "text": "一名貴婦\n娜依拉/法圖娜/拉伊德娜",
        },
        "s5": {
            "guid":"50b24ea6-1565-4dd5-9a3d-d2b9a48f0345",
            "condition": {
                "type": "char",
                "主角":1,
            },
            "open_adsorb": 0,
            "is_key": 0,
            "is_empty": 0,
            "is_enemy": 0,
            "text": "你必須親自到場",
        },
    }
}