{
    "id": 5006149,
    "name": "寵妃的珠寶訂單",
    "text": "一位現在正受寵的妃子——她沒有透露自己的名字——送來了一份訂單，她要熱娜給自己做一件“讓其他女人嫉妒、讓她們恨得發狂”的作品……",
    "tips": "",
    "mapping_id":8001574,
    "once_new": 0,
    "round_number": 2,
    "waiting_round": 0,
    "waiting_round_end_action": [
    ],
    "method_settlement": "",
    "auto_begin": 0,
    "auto_result": 0,
    "location": "自宅:[2,12]",
    "icon": "rite_19",
    "tag_tips": [],
    "tag_tips_up": {

    },
    "tips_text": [
        "蘇丹的妃子，最差最差也得配藍寶石",
        "如果能拿出比藍寶石更名貴的材料，想必更能討貴人的歡心",

    ],
    "open_conditions": [
        {
            "condition": {
                "any":{
                   "s3.紅寶石":1,
                   "s3.藍寶石":1,
                   "s3.鑽石":1,
                },
            },
            "tips": "請放入合適的寶石，要大顆的"
        }
    ],
    "random_text": {},
    "random_text_up": {

    },
    "settlement_prior": [

    ],
    "settlement": [
         {
            "guid":"44109814-97f1-45b2-a6f3-021c4ad6e8af",
            "condition": {
                "s3.紅寶石":1,
            },
            "result_title": "這點錢只夠買紅寶石",
            "result_text": "你總感覺這訂單有問題，畢竟真正的寵妃可不會自稱是寵妃，就好比真正的蘇丹不需要通報自己的姓名，再加上隨訂單送來的金幣就那麼幾枚，只夠買一顆還算過得去的紅寶石，你就更加確定這女人絕對沒有受寵了。\n你讓熱娜用紅寶石來完成這件首飾，對一般人來說，這是火一般灼手的珍寶，但對一個真正的寵妃來說，這石頭可能只能換來一小點愉悅——大概指甲蓋那麼大的一小點兒。\n熱娜把這串紅寶石項鍊送進宮裡去之後，那位寵妃卻再也沒有回過信，甚至連個便條都沒捎來，更別提什麼許諾的賞賜了……\n熱娜沮喪地把這筆訂單的收益全都給了你，這件事就這麼過去了，或許你們被某個根本沒資格侍寢的女人給騙了，又或許你們做了一樁投資……誰知道呢？",
            "result": {
                "clean.s3":1,  //消除珠寶
                "金幣":9,
                "s1+靈感":10,
                "counter+7000821":1,  //完成一個宮廷訂單的計數器
                "counter+7000831":1  //寵妃的珠寶給了紅寶石，對應安蘇亞
            },
            "action": {
               "event_on":5320606  //啓動接珠寶訂單的幕後
            }
        },
         {
            "guid":"48f4d6bd-de78-4749-b336-df7334830235",
            "condition": {
                "s3.藍寶石":1,
            },
            "result_title": "微小的快樂",
            "result_text": "你嘆了口氣，會說自己是“寵妃”，就說明這個女人現在並不是寵妃。\n蘇丹的後宮裡充滿了不快樂的女人，因為他不允許女人們為了除自己之外的任何人或事而感到快樂。雖說發來這份訂單的女人或許是在撒謊，但讓她開心點又能怎麼樣呢？\n你建議熱娜用藍寶石完成訂單，這種寶石對莎姬之類的寵妃來說算不得至寶，但它怎麼也都是配得上維齊爾的石頭；訂單背後的人一定會很開心。\n熱娜點點頭，按你的吩咐去準備了。她打了一隻漂亮的金鐲子，鑲嵌上大塊的藍寶石，信心滿滿地把它送進宮裡去之後，那位寵妃卻再也沒有回過信，甚至連個便條都沒捎來……\n好在，這完全在你們的預期之中。熱娜大方地把這筆訂單的收益全都給了你，這件事就這麼過去了，或許你們被某個根本沒資格侍寢的女人給騙了，又或許你們做了一樁投資……誰知道呢？",
            "result": {
                "clean.s3":1,  //消除珠寶
                "金幣":9,
                "s1+靈感":15,
                "counter+7000821":1,  //完成一個宮廷訂單的計數器
                "counter+7000830":1  //寵妃的珠寶給了藍寶石，對應薩達爾尼
            },
            "action": {
               "event_on":5320606  //啓動接珠寶訂單的幕後
            }
        },
         {
            "guid":"f354d608-f6ff-43c1-aaa8-9e17443d7c82",
            "condition": {
                "s3.鑽石":1,
            },
            "result_title": "鑽石才配得上蘇丹最寵愛的妃子",
            "result_text": "用鑽石之外的寶石，根本顯示不出你們對如此寵妃的尊重！\n於是，儘管這位寵妃付來的定金根本不夠鑽石的開銷，你還是建議熱娜使用這種珍貴的寶石來製作這件珠寶，還慷慨了給了她一塊非常罕見的大顆鑽石作為材料。熱娜高興壞了！即使是她這樣的珠寶匠，也不常能夠摸到這麼大塊的鑽石！很快，她把一隻精雕細琢的鑽石戒指送進了宮，可那位寵妃卻再也沒有回過信，甚至連個便條都沒捎來……\n她肯定是個騙子！熱娜簡直覺得天塌了！那位“寵妃”只給了9枚金幣做定金，而你們卻賠進去了這麼大一塊寶石！她含淚忍痛把那些金幣全都給了你，希望能稍微彌補你的損失——身為有追求的珠寶匠，至少她在製作這枚珠寶的時候得到了不少快樂。",
            "result": {
                "clean.s3":1,  //消除珠寶
                "金幣":9,
                "s1+靈感":20,
                "counter+7000821":1,  //完成一個宮廷訂單的計數器
                "counter+7000829":1  //寵妃的珠寶給了鑽石，對應金妃
            },
            "action": {
               "event_on":5320606  //啓動接珠寶訂單的幕後
            }
        }
    ],
    "settlement_extre": [

    ],
    "cards_slot": {
        "s1": {
            "guid":"a1a66719-d6d6-4335-861b-a40efe22ebc6",
            "condition": {
                "type": "char",
                "is":2000019 //熱娜
            },
            "open_adsorb": 0,
            "is_key": 0,
            "is_empty": 0,
            "is_enemy": 0,
            "text": "熱娜",

        },
        "s2": {
            "guid":"ac4096d5-4d38-48fb-966b-1fadca19d6e2",
            "condition": {
                "type": "item",
                "cost.金幣=":5
            },
            "open_adsorb": 0,
            "is_key": 0,
            "is_empty": 0,
            "is_enemy": 0,
            "text": "另需5金幣購買其他材料",
        },
        "s3": {
            "guid":"09a92108-9462-440d-b888-1d36920384b6",
            "condition": {
                "type": "item",
                "寶石":1,
                "大顆":1,
                "cost.可堆疊=":1
            },
            "open_adsorb": 0,
            "is_key": 0,
            "is_empty": 0,
            "is_enemy": 0,
            "text": "合適的寶石，要大顆的\n紅寶石：熱娜靈感+10，金幣+9\n藍寶石：熱娜靈感+15，金幣+9\n鑽石：熱娜靈感+20，金幣+9",
            "pops":[
                {
                    "condition":{
                        "s3.紅寶石":1
                    },
                    "action":{
                        "pop.5006149_s3_01.self":"她隨單附送的金幣只夠買紅寶石的，就用紅寶石吧。",
                    }
                },
                {
                    "condition":{
                        "any":{
                            "s3.藍寶石":1,
                            "s3.鑽石":1,
                        },
                    },
                    "action":{
                        "pop.5006149_s3_02.self":"這塊寶石配得上宮中貴人的身份",
                    }
                },
                {
                    "condition":{
                        "!s3.紅寶石":1,
                        "!s3.藍寶石":1,
                        "!s3.鑽石":1,
                    },
                    "action":{
                        "pop.5006149_s3_03.self":"這塊寶石對貴人來說太掉價了",
                    }
                }
            ]
        }
    }
}